README.rst
setup.py
django_redis_pubsub.egg-info/PKG-INFO
django_redis_pubsub.egg-info/SOURCES.txt
django_redis_pubsub.egg-info/dependency_links.txt
django_redis_pubsub.egg-info/requires.txt
django_redis_pubsub.egg-info/top_level.txt
redis_pubsub/__init__.py
redis_pubsub/apps.py
redis_pubsub/auth.py
redis_pubsub/compat.py
redis_pubsub/models.py
redis_pubsub/receivers.py
redis_pubsub/util.py
redis_pubsub/contrib/__init__.py
redis_pubsub/contrib/websockets/__init__.py
redis_pubsub/contrib/websockets/util.py
redis_pubsub/management/__init__.py
redis_pubsub/management/commands/__init__.py
redis_pubsub/management/commands/async_runserver.py
redis_pubsub/migrations/0001_initial.py
redis_pubsub/migrations/__init__.py
testapp/migrations/0001_initial.py
testapp/migrations/__init__.py