Metadata-Version: 1.1
Name: django-redis-pubsub
Version: 1.0
Summary: asyncronous pubsub in django using redis
Home-page: https://github.com/andrewyoung1991/django-redis-pubsub
Author: Andrew Young
Author-email: UNKNOWN
License: BSD
Platform: UNKNOWN
Classifier: Development Status :: 3 - Alpha
Classifier: Intended Audience :: Developers
Classifier: Environment :: Web Environment
Classifier: Framework :: Django
Classifier: License :: OSI Approved :: BSD License
Classifier: Operating System :: OS Independent
Classifier: Programming Language :: Python
Classifier: Programming Language :: Python :: 3.4
Classifier: Programming Language :: Python :: 3.5
